<?xml version="1.0" encoding="UTF-8"?>

<!-- generated on 2023-12-08 19:54:30 by Eclipse SUMO GUI Version 1.17.0
<configuration xmlns:xsi="http://www.w3.org/2001/XMLSchema-instance" xsi:noNamespaceSchemaLocation="http://sumo.dlr.de/xsd/sumoConfiguration.xsd">

    <input>
        <net-file value="shortramp.net.xml"/>
        <route-files value="shortramp.rou.xml"/>
        <additional-files value="detector.add.xml"/>
    </input>

    <time>
        <begin value="0"/>
        <end value="5400"/>
    </time>

    <processing>
        <extrapolate-departpos value="true"/>
        <time-to-teleport value="-1"/>
        <max-depart-delay value="-1"/>
        <emergency-insert value="true"/>
    </processing>

    <traci_server>
        <remote-port value="51922"/>
    </traci_server>

    <random_number>
        <seed value="123"/>
    </random_number>

    <gui_only>
        <start value="true"/>
    </gui_only>

</configuration>
-->

<detector xmlns:xsi="http://www.w3.org/2001/XMLSchema-instance" xsi:noNamespaceSchemaLocation="http://sumo.dlr.de/xsd/det_e1_file.xsd">
    <interval begin="0.00" end="300.00" id="e1_VM2" nVehContrib="118" flow="1416.00" occupancy="5.84" speed="30.50" harmonicMeanSpeed="30.33" length="4.50" nVehEntered="118"/>
    <interval begin="300.00" end="365.00" id="e1_VM2" nVehContrib="26" flow="1440.00" occupancy="5.71" speed="31.65" harmonicMeanSpeed="31.53" length="4.50" nVehEntered="26"/>
</detector>
